tfcaidm/__init__.py
tfcaidm/benchmarks/__init__.py
tfcaidm/benchmarks/benchmark.py
tfcaidm/common/__init__.py
tfcaidm/common/constants.py
tfcaidm/common/inherit.py
tfcaidm/common/reproducibility.py
tfcaidm/common/timedate.py
tfcaidm/data/__init__.py
tfcaidm/data/dataset.py
tfcaidm/data/jclient.py
tfcaidm/data/utils/__init__.py
tfcaidm/data/utils/class_weights.py
tfcaidm/data/utils/positional_encoding.py
tfcaidm/jobs/__init__.py
tfcaidm/jobs/job.py
tfcaidm/jobs/utils/__init__.py
tfcaidm/jobs/utils/config.py
tfcaidm/jobs/utils/env.py
tfcaidm/jobs/utils/params.py
tfcaidm/jobs/utils/tool.py
tfcaidm/losses/__init__.py
tfcaidm/losses/loss.py
tfcaidm/losses/custom/__init__.py
tfcaidm/losses/custom/_zoo.py
tfcaidm/losses/custom/registry.py
tfcaidm/losses/funcs/__init__.py
tfcaidm/losses/funcs/dice.py
tfcaidm/losses/funcs/distance.py
tfcaidm/losses/funcs/entropy.py
tfcaidm/losses/funcs/focal.py
tfcaidm/losses/funcs/tversky.py
tfcaidm/metrics/__init__.py
tfcaidm/metrics/metric.py
tfcaidm/metrics/custom/__init__.py
tfcaidm/metrics/custom/_zoo.py
tfcaidm/metrics/custom/registry.py
tfcaidm/metrics/funcs/__init__.py
tfcaidm/metrics/funcs/acc.py
tfcaidm/metrics/funcs/dice.py
tfcaidm/metrics/funcs/distance.py
tfcaidm/models/__init__.py
tfcaidm/models/model.py
tfcaidm/models/blocks/__init__.py
tfcaidm/models/blocks/atrous_block.py
tfcaidm/models/blocks/attention_gate.py
tfcaidm/models/blocks/cbam_block.py
tfcaidm/models/blocks/convgru_cell.py
tfcaidm/models/blocks/csp_block.py
tfcaidm/models/blocks/dense_block.py
tfcaidm/models/blocks/eca_block.py
tfcaidm/models/blocks/inception_block.py
tfcaidm/models/blocks/psp_block.py
tfcaidm/models/blocks/se_block.py
tfcaidm/models/blocks/separable_conv.py
tfcaidm/models/blocks/u2net_block.py
tfcaidm/models/custom/__init__.py
tfcaidm/models/custom/_zoo.py
tfcaidm/models/custom/registry.py
tfcaidm/models/layers/__init__.py
tfcaidm/models/layers/activation.py
tfcaidm/models/layers/extra.py
tfcaidm/models/layers/learner.py
tfcaidm-0.0.0a4.dist-info/LICENSE
tfcaidm-0.0.0a4.dist-info/METADATA
tfcaidm-0.0.0a4.dist-info/WHEEL
tfcaidm-0.0.0a4.dist-info/top_level.txt
tfcaidm-0.0.0a4.dist-info/RECORD
