Metadata-Version: 2.1
Name: tfcaidm
Version: 0.0.0a4
Summary: Deep learning pipeline for medical imaging
Home-page: https://github.com/Brandhsu/tfcaidm
Author: Brandhsu
Author-email: brandondhsu@gmail.com
License: GPLv3
Keywords: deep learning,neural networks,medical imaging,computer vision
Platform: UNKNOWN
Classifier: Development Status :: 3 - Alpha
Classifier: Intended Audience :: Developers
Classifier: License :: OSI Approved :: GNU General Public License v3 (GPLv3)
Classifier: Programming Language :: Python :: 3.6
Classifier: Programming Language :: Python :: 3.7
Classifier: Programming Language :: Python :: 3.8
Classifier: Programming Language :: Python :: 3.9
Requires-Python: >=3.6
License-File: LICENSE
Requires-Dist: matplotlib
Requires-Dist: numpy
Requires-Dist: pandas
Requires-Dist: pytz
Requires-Dist: ruamel.yaml (==0.17.17)
Requires-Dist: scikit-learn
Requires-Dist: scipy
